flask_shell2http/__init__.py
flask_shell2http/api.py
flask_shell2http/base_entrypoint.py
flask_shell2http/classes.py
flask_shell2http/exceptions.py
flask_shell2http/helpers.py
Flask_Shell2HTTP_fork-1.9.2.dist-info/LICENSE
Flask_Shell2HTTP_fork-1.9.2.dist-info/METADATA
Flask_Shell2HTTP_fork-1.9.2.dist-info/WHEEL
Flask_Shell2HTTP_fork-1.9.2.dist-info/top_level.txt
Flask_Shell2HTTP_fork-1.9.2.dist-info/RECORD
