Metadata-Version: 2.1
Name: Flask-Shell2HTTP-fork
Version: 1.9.2
Summary: A minimalist REST API wrapper for python's subprocess API.
Home-page: https://github.com/intelowlproject/flask-shell2http
Author: Eshaan Bansal
Author-email: eshaan7bansal@gmail.com
License: BSD
Project-URL: Documentation, https://github.com/intelowlproject/flask-shell2http
Project-URL: Funding, https://www.paypal.me/eshaanbansal
Project-URL: Source, https://github.com/intelowlproject/flask-shell2http
Project-URL: Tracker, https://github.com/intelowlproject/flask-shell2http/issues
Keywords: flask shell2http subprocess python
Platform: any
Classifier: Environment :: Web Environment
Classifier: Intended Audience :: Developers
Classifier: Operating System :: OS Independent
Classifier: License :: OSI Approved :: BSD License
Classifier: Programming Language :: Python :: 3
Classifier: Programming Language :: Python :: 3.6
Classifier: Programming Language :: Python :: 3.7
Classifier: Programming Language :: Python :: 3.8
Classifier: Programming Language :: Python :: 3.9
Classifier: Programming Language :: Python :: 3.10
Classifier: Topic :: Internet :: WWW/HTTP :: Dynamic Content
Classifier: Topic :: Software Development :: Libraries :: Python Modules
Requires-Python: >= 3.6
License-File: LICENSE
Requires-Dist: flask (>=1.0.0)
Requires-Dist: blinker
Requires-Dist: flask-executor
Requires-Dist: contextvars ; python_version < "3.7"
Provides-Extra: test
Requires-Dist: flask (>=1.0.0) ; extra == 'test'
Requires-Dist: blinker ; extra == 'test'
Requires-Dist: flask-executor ; extra == 'test'
Requires-Dist: flask-testing ; extra == 'test'
Requires-Dist: coverage ; extra == 'test'
Requires-Dist: tox ; extra == 'test'
Requires-Dist: tox-gh-actions ; extra == 'test'
Requires-Dist: black (==22.3.0) ; extra == 'test'
Requires-Dist: flake8 (==3.8.4) ; extra == 'test'
Requires-Dist: pre-commit (==2.9.2) ; extra == 'test'
Requires-Dist: contextvars ; (python_version < "3.7") and extra == 'test'
